{
	"IcoMoonType": "selection",
	"icons": [],
	"height": 1024,
	"metadata": {
		"name": "evo-icon-font-app"
	},
	"preferences": {
		"showGlyphs": true,
		"showQuickUse": true,
		"showQuickUse2": true,
		"showSVGs": true,
		"fontPref": {
			"prefix": "evo-icon-app-",
			"metadata": {
				"fontFamily": "evo-icon-font-app",
				"majorVersion": 1,
				"minorVersion": 0
			},
			"metrics": {
				"emSize": 1024,
				"baseline": 6.25,
				"whitespace": 50
			},
			"embed": false,
			"showSelector": true,
			"selector": "class",
			"classSelector": ".icon",
			"showMetrics": true,
			"showMetadata": true,
			"showVersion": true,
			"includeMetadata": false,
			"noie8": false,
			"ie7": false
		},
		"imagePref": {
			"prefix": "icon-",
			"png": true,
			"useClassSelector": true,
			"color": 10066329,
			"bgColor": 16777215,
			"classSelector": ".icon",
			"columns": 16,
			"margin": 16,
			"height": 32
		},
		"historySize": 100,
		"showCodes": true,
		"gridSize": 16,
		"showLiga": false
	}
}